{
  "description": "项目配置文件",
  "packOptions": {
    "ignore": [
      {
        "value": ".eslintrc.js",
        "type": "file"
      }
    ],
    "include": []
  },
  "setting": {
    "urlCheck": false,
    "es6": true,
    "enhance": true,
    "postcss": true,
    "preloadBackgroundData": false,
    "minified": true,
    "newFeature": false,
    "coverView": true,
    "nodeModules": false,
    "autoAudits": false,
    "showShadowRootInWxmlPanel": true,
    "scopeDataCheck": false,
    "uglifyFileName": false,
    "checkInvalidKey": true,
    "checkSiteMap": true,
    "uploadWithSourceMap": true,
    "compileHotReLoad": false,
    "lazyloadPlaceholderEnable": false,
    "useMultiFrameRuntime": true,
    "useApiHook": true,
    "useApiHostProcess": true,
    "babelSetting": {
      "ignore": [],
      "disablePlugins": [],
      "outputPath": ""
    },
    "enableEngineNative": false,
    "useIsolateContext": true,
    "userConfirmedBundleSwitch": false,
    "packNpmManually": false,
    "packNpmRelationList": [],
    "minifyWXSS": true,
    "disableUseStrict": false,
    "minifyWXML": true,
    "showES6CompileOption": false,
    "useCompilerPlugins": false,
    "compileWorklet": false,
    "localPlugins": false,
    "condition": false,
    "swc": false,
    "disableSWC": true
  },
  "compileType": "miniprogram",
  "libVersion": "2.19.4",
  "appid": "wx073d0aa7778622da",
  "projectname": "ADIRP数智招聘",
  "isGameTourist": false,
  "condition": {
    "search": {
      "list": []
    },
    "conversation": {
      "list": []
    },
    "game": {
      "list": []
    },
    "plugin": {
      "list": []
    },
    "gamePlugin": {
      "list": []
    },
    "miniprogram": {
      "list": [
        {
          "name": "首页",
          "pathName": "pages/index/index",
          "query": "",
          "scene": null
        },
        {
          "name": "登录",
          "pathName": "pages/login/login",
          "query": "",
          "scene": null
        },
        {
          "name": "职位列表",
          "pathName": "pages/jobs/jobs",
          "query": "",
          "scene": null
        },
        {
          "name": "聊天",
          "pathName": "pages/chat/chat",
          "query": "",
          "scene": null
        },
        {
          "name": "个人中心",
          "pathName": "pages/profile/profile",
          "query": "",
          "scene": null
        }
      ]
    }
  },
  "simulatorPluginLibVersion": {},
  "editorSetting": {}
}